greopy/__init__.py
greopy/_solversetupconfig.py
greopy/common.py
greopy/config.py
greopy/emitter_observer_problem.py
greopy/emitter_observer_solution_plot.py
greopy/initial_conditions.py
greopy/metric_config_numpy.py
greopy/metric_config_sympy.py
greopy/orbit_calc.py
greopy-1.0.dist-info/METADATA
greopy-1.0.dist-info/WHEEL
greopy-1.0.dist-info/licenses/LICENSE
greopy-1.0.dist-info/RECORD
