Metadata-Version: 2.4
Name: GREOPy
Version: 1.0
Summary: Solve the general-relativistic Emitter-Observer problem.
Author-email: Jan Patrick Hackstein <jan.hackstein@zarm.uni-bremen.de>
Maintainer-email: Jan Patrick Hackstein <jan.hackstein@zarm.uni-bremen.de>
License-Expression: GPL-3.0-only
License-File: LICENSE
Requires-Python: >=3.9
Requires-Dist: matplotlib>=3.8
Requires-Dist: pandas>=2.2
Requires-Dist: scipy>=1.7.2
Requires-Dist: sympy>=1.2
Provides-Extra: dev
Requires-Dist: hatch; extra == 'dev'
Requires-Dist: tables; extra == 'dev'
Requires-Dist: tomli; extra == 'dev'
Provides-Extra: docs
Requires-Dist: sphinx-gallery; extra == 'docs'
Provides-Extra: external-data
Requires-Dist: tables; extra == 'external-data'
Requires-Dist: tomli; extra == 'external-data'
